{
  "version": "7",
  "dialect": "postgresql",
  "entries": [
    {
      "idx": 0,
      "version": "7",
      "when": 1721571299951,
      "tag": "0000_loving_korath",
      "breakpoints": true
    },
    {
      "idx": 1,
      "version": "7",
      "when": 1721650689192,
      "tag": "0001_classy_fixer",
      "breakpoints": true
    },
    {
      "idx": 2,
      "version": "7",
      "when": 1721905134052,
      "tag": "0002_sad_red_hulk",
      "breakpoints": true
    },
    {
      "idx": 3,
      "version": "7",
      "when": 1722002189041,
      "tag": "0003_typical_valkyrie",
      "breakpoints": true
    },
    {
      "idx": 4,
      "version": "7",
      "when": 1722045431317,
      "tag": "0004_special_leopardon",
      "breakpoints": true
    },
    {
      "idx": 5,
      "version": "7",
      "when": 1722045643778,
      "tag": "0005_tidy_stingray",
      "breakpoints": true
    },
    {
      "idx": 6,
      "version": "7",
      "when": 1722045721065,
      "tag": "0006_gifted_hitman",
      "breakpoints": true
    },
    {
      "idx": 7,
      "version": "7",
      "when": 1722086297927,
      "tag": "0007_lyrical_felicia_hardy",
      "breakpoints": true
    }
  ]
}